{
  "metadata": {
    "type": "minor_arcana_wands",
    "suit": "wands",
    "element": "fire",
    "totalCards": 14,
    "completedCards": 14,
    "lastUpdated": "2025-07-28",
    "categories": ["general", "love", "career", "money", "health", "spiritual"],
    "languages": ["ko", "en"]
  },
  
  "cards": [
    {
      "id": 22,
      "name": "Ace of Wands",
      "koreanName": "완드 에이스",
      "suit": "wands",
      "number": 1,
      "element": "fire",
      "uprightKeywords": ["창조", "영감", "새시작", "잠재력", "열정", "혁신", "기회"],
      "reversedKeywords": ["지연", "좌절", "에너지부족", "창의성막힘", "동기상실", "미완성"],
      
      "interpretations": {
        "upright": {
          "general": "강력한 창조적 에너지가 분출하는 시기입니다. 새로운 프로젝트, 아이디어, 기회가 당신 앞에 펼쳐져 있습니다. 열정과 동기가 최고조에 달해 있습니다.",
          "love": "새로운 연애가 시작되거나 기존 관계에 새로운 열정이 불어날 것입니다. 강렬하고 역동적인 사랑을 경험할 수 있습니다.",
          "career": "새로운 직업 기회, 프로젝트, 또는 사업 아이디어가 나타날 것입니다. 창의성과 혁신이 필요한 분야에서 뛰어난 성과를 거둘 수 있습니다.",
          "money": "새로운 수입원이나 투자 기회가 생깁니다. 창의적이거나 혁신적인 사업 아이디어를 통해 수익을 창출할 수 있습니다.",
          "health": "에너지 레벨이 크게 향상되고 활력이 넘치게 될 것입니다. 새로운 운동이나 건강한 라이프스타일을 도입하기 완벽한 시기입니다.",
          "spiritual": "영적 각성이나 새로운 깨달음을 경험할 수 있습니다. 창조적 영감과 영적 통찰이 결합될 것입니다."
        },
        "reversed": {
          "general": "좋은 아이디어와 계획은 있지만 실행에 어려움을 겪고 있습니다. 창조적 에너지가 막히거나 방향을 찾지 못하고 있습니다.",
          "love": "새로운 연애에 대한 기대는 있지만 실제로 만남이 이루어지지 않거나 발전하지 않고 있습니다. 열정이 일방적일 수 있습니다.",
          "career": "새로운 프로젝트나 아이디어가 승인되지 않거나 지연되고 있습니다. 창의성을 발휘할 기회가 주어지지 않을 수 있습니다.",
          "money": "투자나 새로운 사업 기회가 기대만큼 성과를 내지 못하고 있습니다. 자금 조달에 어려움이 있을 수 있습니다.",
          "health": "건강 관리에 대한 의욕이 부족하거나 시작했던 운동을 중단하게 될 수 있습니다. 에너지 레벨이 낮을 수 있습니다.",
          "spiritual": "영적 성장이 정체되어 있거나 방향을 잃었을 수 있습니다. 영적 수행에 대한 동기가 떨어질 수 있습니다."
        }
      },
      
      "timing": {
        "immediate": "새로운 기회나 아이디어가 바로 나타남",
        "shortTerm": "3-6주 동안 창조적 프로젝트에 최적의 시기",
        "longTerm": "6개월 후 현재 아이디어가 구체적인 형태를 갖춤"
      },
      
      "advice": {
        "upright": {
          "action": "떠오르는 아이디어를 즉시 실행에 옮기세요",
          "avoid": "완벽한 계획을 세우려다 시작을 미루지 마세요",
          "focus": "창조적 에너지와 열정 활용"
        },
        "reversed": {
          "action": "창조적 에너지 회복을 위해 휴식을 취하세요",
          "avoid": "좌절감에 빠져 완전히 포기하지 마세요",
          "focus": "작은 것부터 차근차근 시작"
        }
      },
      
      "symbolism": [
        {"symbol": "손에서 나오는 완드", "meaning": "새로운 창조적 힘"},
        {"symbol": "새싹", "meaning": "성장의 시작"},
        {"symbol": "구름", "meaning": "영감과 직감"},
        {"symbol": "산", "meaning": "앞으로의 도전과 성장"}
      ],
      
      "imageUrl": "assets/cards/wands_01_ace.png"
    },
    
    {
      "id": 23,
      "name": "Two of Wands",
      "koreanName": "완드 2",
      "suit": "wands",
      "number": 2,
      "element": "fire",
      "uprightKeywords": ["계획", "미래비전", "개인의힘", "진전", "발견", "기회모색"],
      "reversedKeywords": ["계획부족", "두려움", "급함", "예상밖", "철수"],
      
      "interpretations": {
        "upright": {
          "general": "미래를 계획하고 장기적인 목표를 세울 완벽한 시기입니다. 개인의 힘과 능력을 인식하고 더 큰 가능성을 탐색하세요.",
          "love": "관계의 미래에 대해 진지하게 생각해볼 때입니다. 파트너와 함께 장기적인 계획을 세우거나 새로운 관계의 가능성을 탐색할 수 있습니다.",
          "career": "현재 위치에서 더 큰 기회를 모색하고 있습니다. 새로운 파트너십이나 해외 진출 등 확장의 기회가 있을 수 있습니다.",
          "money": "투자나 사업 확장에 대한 계획을 세우기 좋은 시기입니다. 장기적인 재정 목표를 설정하고 실행 계획을 만드세요.",
          "health": "건강 관리에 대한 장기적인 계획이 필요합니다. 새로운 운동 방법이나 다이어트를 시작하기 좋은 때입니다.",
          "spiritual": "영적 성장의 다음 단계를 계획하고 있습니다. 새로운 영적 가르침이나 수행법을 탐구해볼 수 있습니다."
        },
        "reversed": {
          "general": "계획 없이 성급하게 행동하려 하고 있습니다. 미래에 대한 두려움이나 불안감이 결정을 방해하고 있을 수 있습니다.",
          "love": "관계의 미래에 대한 불안감이나 불확실성을 느끼고 있습니다. 파트너와의 소통이 부족하거나 계획이 맞지 않을 수 있습니다.",
          "career": "직업적 방향성을 잃었거나 기회를 놓치고 있을 수 있습니다. 준비 부족으로 인해 좋은 기회를 활용하지 못할 수 있습니다.",
          "money": "재정 계획이 부실하거나 예상치 못한 지출로 인해 어려움을 겪을 수 있습니다. 단기적 사고로 인한 손실을 주의하세요.",
          "health": "건강 관리에 일관성이 부족하거나 계획적이지 못합니다. 즉석에서 내리는 건강 결정들이 도움이 되지 않을 수 있습니다.",
          "spiritual": "영적 성장에 대한 명확한 방향이 없거나 여러 길 사이에서 혼란을 느끼고 있습니다."
        }
      },
      
      "timing": {
        "immediate": "장기 계획 수립을 시작해야 할 때",
        "shortTerm": "6-8주 동안 미래 비전이 명확해짐",
        "longTerm": "6개월 후 계획한 것들이 구체화됨"
      },
      
      "advice": {
        "upright": {
          "action": "장기적인 목표를 설정하고 단계별 계획을 세우세요",
          "avoid": "현재 상황에만 안주하지 마세요",
          "focus": "미래 비전과 확장 가능성"
        },
        "reversed": {
          "action": "충분한 계획과 준비를 한 후에 행동하세요",
          "avoid": "불안감에 사로잡혀 기회를 놓치지 마세요",
          "focus": "체계적인 준비와 현실적인 계획"
        }
      },
      
      "symbolism": [
        {"symbol": "지구본", "meaning": "세계적 관점과 확장"},
        {"symbol": "성벽", "meaning": "견고한 기반과 보호"},
        {"symbol": "먼 풍경", "meaning": "미래의 가능성"},
        {"symbol": "두 번째 완드", "meaning": "선택과 결정"}
      ],
      
      "imageUrl": "assets/cards/wands_02_two.png"
    },
    
    {
      "id": 24,
      "name": "Three of Wands",
      "koreanName": "완드 3",
      "suit": "wands",
      "number": 3,
      "element": "fire",
      "uprightKeywords": ["확장", "전망", "미래계획", "해외진출", "협력", "성장", "리더십"],
      "reversedKeywords": ["지연", "좌절", "계획실패", "협력부족", "근시안적사고", "고립"],
      
      "interpretations": {
        "upright": {
          "general": "당신의 노력이 결실을 맺고 있으며, 더 큰 기회와 확장의 가능성이 열리고 있습니다. 장기적인 계획이 성공적으로 진행되고 있습니다.",
          "love": "관계가 다음 단계로 발전할 가능성이 높습니다. 원거리 연애나 국제적인 만남의 기회가 있을 수 있습니다.",
          "career": "사업이나 프로젝트가 확장되고 있습니다. 해외 진출이나 새로운 파트너십의 기회가 있을 수 있습니다.",
          "money": "투자나 사업이 예상보다 좋은 성과를 보이고 있습니다. 해외 투자나 수출 관련 수익이 증가할 수 있습니다.",
          "health": "건강 상태가 개선되고 있으며, 새로운 치료법이나 건강 관리 방법이 효과를 보이고 있습니다.",
          "spiritual": "영적 성장이 확장되고 있으며, 새로운 영적 커뮤니티나 가르침과 연결될 수 있습니다."
        },
        "reversed": {
          "general": "계획이 예상보다 지연되거나 어려움에 직면하고 있습니다. 혼자 힘으로는 한계가 있으니 협력이 필요합니다.",
          "love": "관계 발전이 더디거나 거리의 문제로 어려움을 겪을 수 있습니다. 소통과 인내가 필요합니다.",
          "career": "프로젝트 진행이 늦어지거나 예상치 못한 장애물에 부딪힐 수 있습니다. 협력자나 파트너와의 갈등을 주의하세요.",
          "money": "투자 수익이 기대에 못 미치거나 해외 관련 투자에서 손실을 볼 수 있습니다. 신중한 재검토가 필요합니다.",
          "health": "치료 과정이 지연되거나 기대한 만큼 빠른 회복이 어려울 수 있습니다. 인내심을 갖고 꾸준히 관리하세요.",
          "spiritual": "영적 성장이 정체되어 있거나 혼자만의 수행으로는 한계를 느낄 수 있습니다. 멘토나 동료가 필요합니다."
        }
      },
      
      "timing": {
        "immediate": "계획의 첫 번째 성과가 나타나는 시점",
        "shortTerm": "3-4개월 동안 확장과 성장이 활발",
        "longTerm": "1년 후 국제적 또는 대규모 성과 달성"
      },
      
      "advice": {
        "upright": {
          "action": "더 큰 비전을 품고 확장 기회를 적극적으로 추진하세요",
          "avoid": "현재 성과에 안주하지 마세요",
          "focus": "장기적 관점과 협력적 접근"
        },
        "reversed": {
          "action": "계획을 재검토하고 협력 파트너를 찾으세요",
          "avoid": "혼자 모든 것을 해결하려 하지 마세요",
          "focus": "인내심과 협력을 통한 문제해결"
        }
      },
      
      "symbolism": [
        {"symbol": "먼 바다", "meaning": "미래의 기회와 가능성"},
        {"symbol": "배들", "meaning": "진행 중인 프로젝트와 협력"},
        {"symbol": "높은 언덕", "meaning": "넓은 시야와 전망"},
        {"symbol": "세 개의 완드", "meaning": "협력과 확장의 기반"}
      ],
      
      "imageUrl": "assets/cards/wands_03_three.png"
    },
    
    {
      "id": 25,
      "name": "Four of Wands",
      "koreanName": "완드 4",
      "suit": "wands",
      "number": 4,
      "element": "fire",
      "uprightKeywords": ["축하", "안정", "결혼", "가정", "성취", "화합", "완성"],
      "reversedKeywords": ["불화", "지연", "불안정", "갈등", "축하연기", "가족문제"],
      
      "interpretations": {
        "upright": {
          "general": "중요한 목표를 달성하고 축하할 일이 생깁니다. 안정적인 기반이 마련되어 평화롭고 조화로운 시기를 보낼 수 있습니다.",
          "love": "결혼이나 약혼 등 관계의 중요한 이정표를 맞이할 수 있습니다. 가족들의 축복을 받는 행복한 시기입니다.",
          "career": "프로젝트의 성공적인 완료나 승진 등 직장에서 축하받을 일이 생깁니다. 팀워크가 좋아져 화합의 분위기가 조성됩니다.",
          "money": "재정적 안정을 이루거나 큰 수익을 얻어 축하할 일이 생깁니다. 가족과 함께 경제적 풍요를 누릴 수 있습니다.",
          "health": "건강이 크게 개선되어 회복을 축하할 수 있습니다. 가족들과 함께 건강한 생활을 유지할 수 있는 환경이 조성됩니다.",
          "spiritual": "영적 성취나 깨달음을 얻어 내면의 평화와 조화를 경험합니다. 영적 공동체와의 유대감이 깊어집니다."
        },
        "reversed": {
          "general": "기대했던 축하나 성취가 지연되거나 문제가 발생합니다. 가정이나 공동체 내에서 갈등이 있을 수 있습니다.",
          "love": "결혼이나 중요한 관계 결정이 미뤄지거나 가족의 반대에 부딪힐 수 있습니다. 관계의 불안정성을 느낄 수 있습니다.",
          "career": "팀 내 갈등이나 프로젝트 지연으로 인해 축하가 연기될 수 있습니다. 직장 내 화합에 문제가 생길 수 있습니다.",
          "money": "예상했던 수익이 나오지 않거나 가족 간 재정 문제로 갈등이 생길 수 있습니다. 경제적 불안정을 경험할 수 있습니다.",
          "health": "회복이 지연되거나 가족 건강 문제로 걱정이 생길 수 있습니다. 건강 관리에 일관성이 부족할 수 있습니다.",
          "spiritual": "영적 성장이 막히거나 영적 공동체와의 관계에서 갈등을 경험할 수 있습니다. 내면의 조화를 잃을 수 있습니다."
        }
      },
      
      "timing": {
        "immediate": "축하할 일이나 완성의 순간이 곧 다가옴",
        "shortTerm": "4-6주 동안 안정과 조화의 시기",
        "longTerm": "6개월 후 견고한 기반 위에서 새로운 시작"
      },
      
      "advice": {
        "upright": {
          "action": "성취를 축하하고 가족, 친구들과 기쁨을 나누세요",
          "avoid": "성공에 도취되어 다음 목표를 잊지 마세요",
          "focus": "감사함과 조화로운 관계 유지"
        },
        "reversed": {
          "action": "갈등의 원인을 파악하고 화해를 시도하세요",
          "avoid": "불화를 키우거나 축하를 완전히 포기하지 마세요",
          "focus": "인내심과 화합을 통한 문제해결"
        }
      },
      
      "symbolism": [
        {"symbol": "4개의 기둥", "meaning": "안정적인 기반과 구조"},
        {"symbol": "꽃다발", "meaning": "축하와 기쁨"},
        {"symbol": "성문", "meaning": "새로운 단계로의 입구"},
        {"symbol": "춤추는 사람들", "meaning": "공동체의 축제와 화합"}
      ],
      
      "imageUrl": "assets/cards/wands_04_four.png"
    },
    
    {
      "id": 26,
      "name": "Five of Wands",
      "koreanName": "완드 5",
      "suit": "wands",
      "number": 5,
      "element": "fire",
      "uprightKeywords": ["경쟁", "갈등", "도전", "분쟁", "의견차이", "역경", "시험"],
      "reversedKeywords": ["갈등해결", "타협", "팀워크", "협력", "내적갈등", "회피"],
      
      "interpretations": {
        "upright": {
          "general": "경쟁이 치열하거나 의견 충돌이 있는 상황입니다. 다양한 도전과 시험을 통해 자신의 능력을 입증해야 할 때입니다.",
          "love": "관계에서 갈등이나 경쟁 상황이 발생할 수 있습니다. 서로 다른 의견으로 인해 다툼이 있을 수 있지만, 이를 통해 더 깊이 이해하게 됩니다.",
          "career": "직장에서 치열한 경쟁이나 프로젝트를 둘러싼 갈등이 있을 수 있습니다. 여러 사람과 협력하면서 조율이 필요한 상황입니다.",
          "money": "투자나 사업에서 경쟁이 치열하거나 예상치 못한 도전에 직면할 수 있습니다. 신중한 전략이 필요합니다.",
          "health": "건강 관리에 있어 여러 방법 중 선택의 어려움이 있거나 치료 과정에서 시행착오를 겪을 수 있습니다.",
          "spiritual": "영적 성장 과정에서 내적 갈등이나 다양한 가르침 사이에서 혼란을 경험할 수 있습니다. 자신만의 길을 찾아야 합니다."
        },
        "reversed": {
          "general": "갈등이 해결되고 협력의 분위기가 조성됩니다. 경쟁보다는 협력을 통해 더 좋은 결과를 얻을 수 있습니다.",
          "love": "관계의 갈등이 해결되고 서로를 이해하게 됩니다. 타협과 배려를 통해 더 건강한 관계로 발전할 수 있습니다.",
          "career": "팀워크가 개선되고 협력적인 분위기가 조성됩니다. 경쟁보다는 함께 일하는 것의 가치를 깨닫게 됩니다.",
          "money": "재정적 갈등이나 경쟁 상황이 해결됩니다. 협력적 투자나 공동 사업을 통해 더 좋은 결과를 얻을 수 있습니다.",
          "health": "다양한 치료법 중에서 자신에게 맞는 방법을 찾거나 건강 관리 방식이 정착됩니다.",
          "spiritual": "내적 갈등이 해결되고 영적 평화를 찾습니다. 다양한 가르침을 통합하여 자신만의 영적 길을 발견합니다."
        }
      },
      
      "timing": {
        "immediate": "경쟁이나 갈등 상황이 현재 진행 중",
        "shortTerm": "3-5주 동안 도전과 시험의 시기",
        "longTerm": "3개월 후 갈등을 통한 성장과 발전"
      },
      
      "advice": {
        "upright": {
          "action": "건설적인 경쟁을 통해 자신을 발전시키세요",
          "avoid": "불필요한 갈등에 에너지를 소모하지 마세요",
          "focus": "목표 달성을 위한 전략적 접근"
        },
        "reversed": {
          "action": "협력과 타협을 통해 상생의 길을 찾으세요",
          "avoid": "갈등을 완전히 피하기만 하지 마세요",
          "focus": "팀워크와 상호 이해"
        }
      },
      
      "symbolism": [
        {"symbol": "다섯 사람의 싸움", "meaning": "경쟁과 갈등의 상황"},
        {"symbol": "완드들의 충돌", "meaning": "의견과 목표의 대립"},
        {"symbol": "서로 다른 방향", "meaning": "다양한 관점과 접근법"},
        {"symbol": "역동적 움직임", "meaning": "활발한 경쟁과 도전"}
      ],
      
      "imageUrl": "assets/cards/wands_05_five.png"
    },
    
    {
      "id": 27,
      "name": "Six of Wands",
      "koreanName": "완드 6",
      "suit": "wands",
      "number": 6,
      "element": "fire",
      "uprightKeywords": ["승리", "성공", "인정", "공적", "리더십", "자신감", "명예"],
      "reversedKeywords": ["실패", "지연", "자만", "인정부족", "내적성공", "겸손"],
      
      "interpretations": {
        "upright": {
          "general": "노력의 결실을 맺고 주변으로부터 인정받는 시기입니다. 성공과 승리를 거두어 자신감이 크게 향상됩니다.",
          "love": "연애에서 승리하거나 관계가 공개적으로 인정받게 됩니다. 파트너로부터 깊은 사랑과 존경을 받을 수 있습니다.",
          "career": "직장에서 큰 성과를 거두어 승진하거나 인정받게 됩니다. 리더로서의 능력이 인정받아 중요한 역할을 맡게 될 수 있습니다.",
          "money": "투자나 사업에서 큰 성공을 거두어 상당한 수익을 얻습니다. 재정적 목표를 달성하고 안정을 확보합니다.",
          "health": "건강 문제를 성공적으로 극복하거나 건강한 생활습관으로 인한 긍정적 변화를 경험합니다.",
          "spiritual": "영적 성장에서 중요한 성취를 이루고 다른 사람들에게 영감을 주는 존재가 됩니다."
        },
        "reversed": {
          "general": "성공이 지연되거나 기대만큼 인정받지 못하고 있습니다. 겸손한 자세로 내적 성장에 집중해야 할 때입니다.",
          "love": "관계에서 인정받지 못하거나 자만심으로 인해 문제가 생길 수 있습니다. 파트너의 마음을 얻기 위해 더 노력해야 합니다.",
          "career": "기대했던 승진이나 인정이 늦어지고 있습니다. 겸손한 자세로 실력을 더 쌓아야 할 때입니다.",
          "money": "투자 결과가 기대에 못 미치거나 재정적 성공이 지연되고 있습니다. 현실적인 목표 재설정이 필요합니다.",
          "health": "건강 개선이 더디거나 과신으로 인해 건강 관리를 소홀히 할 수 있습니다. 꾸준한 관리가 필요합니다.",
          "spiritual": "영적 성장에서 자만심이나 교만을 경계해야 합니다. 겸손한 자세로 더 깊은 깨달음을 추구하세요."
        }
      },
      
      "timing": {
        "immediate": "성공과 인정의 순간이 곧 찾아옴",
        "shortTerm": "4-6주 동안 승리와 성취의 연속",
        "longTerm": "6개월 후 더 큰 명예와 지위 획득"
      },
      
      "advice": {
        "upright": {
          "action": "성공을 축하하되 겸손함을 잃지 말고 다음 목표를 설정하세요",
          "avoid": "자만심에 빠져 노력을 게을리하지 마세요",
          "focus": "리더십과 책임감"
        },
        "reversed": {
          "action": "내적 성장에 집중하고 겸손한 자세를 유지하세요",
          "avoid": "좌절하거나 포기하지 마세요",
          "focus": "인내심과 지속적인 노력"
        }
      },
      
      "symbolism": [
        {"symbol": "백마", "meaning": "순수한 승리와 고귀함"},
        {"symbol": "월계관", "meaning": "명예와 인정"},
        {"symbol": "환호하는 군중", "meaning": "대중의 찬사와 지지"},
        {"symbol": "기수의 자세", "meaning": "당당함과 자신감"}
      ],
      
      "imageUrl": "assets/cards/wands_06_six.png"
    },
    
    {
      "id": 28,
      "name": "Seven of Wands",
      "koreanName": "완드 7",
      "suit": "wands",
      "number": 7,
      "element": "fire",
      "uprightKeywords": ["방어", "도전", "용기", "고집", "저항", "경쟁", "신념"],
      "reversedKeywords": ["굴복", "패배", "자신감부족", "포기", "압도", "방어실패"],
      
      "interpretations": {
        "upright": {
          "general": "도전받는 상황에서 자신의 입장을 지켜내야 합니다. 어려운 상황이지만 용기와 신념을 갖고 맞서면 승리할 수 있습니다.",
          "love": "관계에서 외부의 간섭이나 도전에 맞서야 할 상황입니다. 사랑을 지키기 위해 용기 있게 행동해야 합니다.",
          "career": "직장에서 경쟁자들의 도전을 받거나 자신의 지위를 방어해야 할 상황입니다. 실력과 의지로 극복할 수 있습니다.",
          "money": "재정적 압박이나 투자에 대한 도전을 받고 있습니다. 신중하면서도 단호한 결정이 필요합니다.",
          "health": "건강 문제와 맞서 싸우고 있지만 강한 의지력으로 극복할 수 있습니다. 포기하지 말고 계속 노력하세요.",
          "spiritual": "신념이나 영적 가치관을 지키기 위해 외부의 압력과 맞서야 할 때입니다. 내적 강함이 필요합니다."
        },
        "reversed": {
          "general": "압박에 굴복하거나 자신의 입장을 포기하고 싶은 상황입니다. 하지만 완전히 포기하기보다는 전략을 재고하세요.",
          "love": "관계를 지키려는 노력이 부족하거나 외부 압력에 굴복할 수 있습니다. 사랑을 위해 더 용기 있게 행동하세요.",
          "career": "경쟁에서 밀리거나 자신의 지위가 위협받고 있습니다. 자신감을 회복하고 새로운 전략이 필요합니다.",
          "money": "재정적 압박에 굴복하거나 투자에서 손실을 볼 수 있습니다. 전문가의 도움을 받아 상황을 재평가하세요.",
          "health": "건강 관리에 대한 의지가 약해지거나 치료를 포기하고 싶어할 수 있습니다. 꾸준한 노력이 필요합니다.",
          "spiritual": "영적 신념이 흔들리거나 외부의 비판에 위축될 수 있습니다. 내적 힘을 기르는 것이 중요합니다."
        }
      },
      
      "timing": {
        "immediate": "도전과 방어가 필요한 상황이 현재 진행 중",
        "shortTerm": "2-4주 동안 치열한 경쟁과 도전",
        "longTerm": "3개월 후 강인한 정신력으로 안정된 지위 확보"
      },
      
      "advice": {
        "upright": {
          "action": "신념을 굽히지 말고 용기 있게 자신의 입장을 지키세요",
          "avoid": "너무 공격적이 되어 불필요한 적을 만들지 마세요",
          "focus": "내적 강함과 전략적 사고"
        },
        "reversed": {
          "action": "전략을 재검토하고 지원군을 찾으세요",
          "avoid": "완전히 포기하거나 자포자기하지 마세요",
          "focus": "자신감 회복과 새로운 접근법"
        }
      },
      
      "symbolism": [
        {"symbol": "높은 절벽", "meaning": "유리한 방어 위치"},
        {"symbol": "올라오는 완드들", "meaning": "도전자들의 공격"},
        {"symbol": "한 사람의 방어", "meaning": "개인의 용기와 의지"},
        {"symbol": "불균형한 신발", "meaning": "불리한 상황에서의 투쟁"}
      ],
      
      "imageUrl": "assets/cards/wands_07_seven.png"
    },
    
    {
      "id": 29,
      "name": "Eight of Wands",
      "koreanName": "완드 8",
      "suit": "wands",
      "number": 8,
      "element": "fire",
      "uprightKeywords": ["속도", "급속진전", "메시지", "여행", "활동", "에너지", "진전"],
      "reversedKeywords": ["지연", "좌절", "소통부족", "급함", "무계획", "방향상실"],
      
      "interpretations": {
        "upright": {
          "general": "모든 일이 빠르게 진행되는 시기입니다. 기다리던 소식이나 기회가 갑자기 찾아오며, 역동적인 변화를 경험하게 됩니다.",
          "love": "연애 진전이 매우 빠르게 이루어집니다. 원거리에서 온 메시지나 만남이 있을 수 있으며, 감정의 교류가 활발해집니다.",
          "career": "업무가 빠르게 진행되고 새로운 기회들이 연달아 찾아옵니다. 출장이나 이동이 잦아질 수 있습니다.",
          "money": "재정 상황이 빠르게 개선되거나 투자 수익이 예상보다 빨리 실현됩니다. 돈의 유입이 활발해집니다.",
          "health": "건강이 빠르게 회복되거나 에너지 레벨이 크게 상승합니다. 활발한 활동으로 체력이 증진됩니다.",
          "spiritual": "영적 깨달음이나 성장이 빠르게 이루어집니다. 새로운 영적 정보나 가르침을 받게 될 수 있습니다."
        },
        "reversed": {
          "general": "예상했던 일들이 지연되거나 급하게 서두르다 실수를 할 수 있습니다. 소통에 문제가 있을 수 있습니다.",
          "love": "관계 진전이 더디거나 상대방과의 소통에 오류가 생길 수 있습니다. 성급한 결정을 피해야 합니다.",
          "career": "프로젝트가 지연되거나 급하게 처리하다 실수를 할 수 있습니다. 출장이나 이동 계획에 차질이 생길 수 있습니다.",
          "money": "투자 수익 실현이 지연되거나 급한 결정으로 인해 손실을 볼 수 있습니다. 신중한 접근이 필요합니다.",
          "health": "회복이 더디거나 과도한 활동으로 인해 피로감을 느낄 수 있습니다. 적절한 휴식이 필요합니다.",
          "spiritual": "영적 성장이 정체되어 있거나 너무 서두르려 해서 중요한 것을 놓칠 수 있습니다. 차분한 접근이 필요합니다."
        }
      },
      
      "timing": {
        "immediate": "빠른 변화와 진전이 바로 시작됨",
        "shortTerm": "1-3주 동안 연속적인 발전과 활동",
        "longTerm": "2개월 후 빠른 변화의 결과가 안정화됨"
      },
      
      "advice": {
        "upright": {
          "action": "빠른 변화에 적응하고 기회를 놓치지 마세요",
          "avoid": "너무 많은 일을 동시에 처리하려 하지 마세요",
          "focus": "신속한 의사결정과 효율적 행동"
        },
        "reversed": {
          "action": "계획을 재검토하고 신중하게 진행하세요",
          "avoid": "조급해하거나 성급한 결정을 내리지 마세요",
          "focus": "인내심과 체계적인 접근"
        }
      },
      
      "symbolism": [
        {"symbol": "8개의 날아가는 완드", "meaning": "빠른 움직임과 진전"},
        {"symbol": "강과 언덕", "meaning": "여행과 이동"},
        {"symbol": "맑은 하늘", "meaning": "명확한 방향성"},
        {"symbol": "평행선", "meaning": "일관된 목표 추진"}
      ],
      
      "imageUrl": "assets/cards/wands_08_eight.png"
    },
    
    {
      "id": 30,
      "name": "Nine of Wands",
      "koreanName": "완드 9",
      "suit": "wands",
      "number": 9,
      "element": "fire",
      "uprightKeywords": ["인내", "끈기", "회복력", "경계", "마지막시험", "방어", "준비"],
      "reversedKeywords": ["포기", "파라노이아", "고집", "의심", "에너지고갈", "경계과다"],
      
      "interpretations": {
        "upright": {
          "general": "많은 시련을 겪었지만 마지막 고비를 넘기면 목표에 도달할 수 있습니다. 지금까지의 노력을 헛되이 하지 말고 조금만 더 버텨내세요.",
          "love": "관계에서 어려움을 겪었지만 서로에 대한 신뢰를 바탕으로 마지막 시험을 통과할 수 있습니다. 인내심이 필요합니다.",
          "career": "프로젝트나 업무에서 마지막 단계의 어려움을 겪고 있지만, 지금까지의 경험과 노하우로 성공적으로 마무리할 수 있습니다.",
          "money": "재정적 어려움의 마지막 고비에 있습니다. 신중한 관리와 인내를 통해 안정을 되찾을 수 있습니다.",
          "health": "건강 회복의 마지막 단계에 있습니다. 지금까지의 치료와 관리를 계속 유지하면 완전한 회복이 가능합니다.",
          "spiritual": "영적 성장의 중요한 시험 단계에 있습니다. 지금까지의 수행과 깨달음을 바탕으로 더 높은 단계로 나아갈 수 있습니다."
        },
        "reversed": {
          "general": "너무 많은 시련에 지쳐 포기하고 싶어합니다. 하지만 이미 목표에 가까이 와 있으니 조금만 더 견뎌내세요.",
          "love": "관계에서 과도한 의심이나 방어적 태도로 인해 문제가 생길 수 있습니다. 파트너를 더 신뢰해야 합니다.",
          "career": "업무에서 과도한 경계심이나 고집으로 인해 협력에 어려움을 겪을 수 있습니다. 유연한 자세가 필요합니다.",
          "money": "재정 관리에서 지나친 보수성이나 의심으로 인해 기회를 놓칠 수 있습니다. 적절한 위험 감수가 필요합니다.",
          "health": "건강에 대한 과도한 걱정이나 의심으로 인해 스트레스를 받을 수 있습니다. 전문가를 믿고 치료에 집중하세요.",
          "spiritual": "영적 성장에서 의심이나 고집으로 인해 진전이 막힐 수 있습니다. 열린 마음으로 새로운 가르침을 받아들이세요."
        }
      },
      
      "timing": {
        "immediate": "마지막 시험이나 고비가 현재 진행 중",
        "shortTerm": "4-6주 동안 인내와 끈기가 필요한 시기",
        "longTerm": "3-4개월 후 모든 시련을 극복하고 목표 달성"
      },
      
      "advice": {
        "upright": {
          "action": "지금까지의 노력을 믿고 마지막까지 포기하지 마세요",
          "avoid": "피로감에 굴복하거나 방심하지 마세요",
          "focus": "인내심과 경계심의 균형"
        },
        "reversed": {
          "action": "과도한 경계를 늦추고 다른 사람들을 신뢰하세요",
          "avoid": "의심과 불안에 사로잡히지 마세요",
          "focus": "유연성과 신뢰 회복"
        }
      },
      
      "symbolism": [
        {"symbol": "상처 입은 전사", "meaning": "시련을 겪은 경험과 지혜"},
        {"symbol": "8개의 완드 벽", "meaning": "구축된 방어와 보호"},
        {"symbol": "붕대", "meaning": "치유와 회복"},
        {"symbol": "경계하는 자세", "meaning": "신중함과 준비성"}
      ],
      
      "imageUrl": "assets/cards/wands_09_nine.png"
    },
    
    {
      "id": 31,
      "name": "Ten of Wands",
      "koreanName": "완드 10",
      "suit": "wands",
      "number": 10,
      "element": "fire",
      "uprightKeywords": ["부담", "책임", "과로", "성공의대가", "완성", "짐", "헌신"],
      "reversedKeywords": ["부담경감", "위탁", "책임회피", "번아웃", "포기", "해방"],
      
      "interpretations": {
        "upright": {
          "general": "성공을 위해 많은 책임과 부담을 지고 있습니다. 목표 달성이 가까워졌지만 과도한 짐으로 인해 피로감을 느끼고 있습니다.",
          "love": "관계에서 모든 책임을 혼자 지려 하고 있습니다. 파트너와 역할을 분담하고 서로 도움을 주고받는 것이 필요합니다.",
          "career": "업무량이 과도하거나 너무 많은 프로젝트를 동시에 진행하고 있습니다. 성공은 가까워졌지만 균형이 필요합니다.",
          "money": "재정적 성공을 위해 과도한 노력을 기울이고 있습니다. 수익은 있지만 그에 따른 부담도 큽니다.",
          "health": "과로나 스트레스로 인해 건강에 적신호가 켜질 수 있습니다. 휴식과 균형이 필요합니다.",
          "spiritual": "영적 성장을 위해 너무 많은 의무를 스스로에게 부과하고 있습니다. 단순함과 본질에 집중해야 합니다."
        },
        "reversed": {
          "general": "무거운 짐을 내려놓거나 책임을 다른 사람에게 위임할 때입니다. 번아웃을 피하고 자유로움을 되찾을 수 있습니다.",
          "love": "관계에서 일방적인 희생을 그만두고 균형잡힌 관계를 만들어가야 합니다. 자신의 행복도 중요합니다.",
          "career": "과도한 업무에서 벗어나거나 책임을 분담할 수 있는 방법을 찾아야 합니다. 효율성을 높이고 우선순위를 정하세요.",
          "money": "재정적 부담을 줄이거나 더 효율적인 수익 방법을 찾을 수 있습니다. 무리한 투자나 지출을 줄이세요.",
          "health": "건강 회복을 위해 휴식을 취하고 스트레스 요인을 제거해야 합니다. 자신을 돌보는 시간이 필요합니다.",
          "spiritual": "영적 성장에서 복잡함을 버리고 단순한 진리에 집중해야 합니다. 과도한 수행보다는 내면의 평화를 추구하세요."
        }
      },
      
      "timing": {
        "immediate": "부담과 책임이 최고조에 달한 상태",
        "shortTerm": "6-8주 동안 과중한 짐을 견뎌내야 하는 시기",
        "longTerm": "4-6개월 후 부담이 줄어들고 성과를 누리게 됨"
      },
      
      "advice": {
        "upright": {
          "action": "목표 달성까지 조금만 더 견뎌내되 건강을 챙기세요",
          "avoid": "모든 것을 혼자 해결하려 하지 마세요",
          "focus": "효율성과 우선순위 설정"
        },
        "reversed": {
          "action": "불필요한 짐을 내려놓고 도움을 요청하세요",
          "avoid": "책임을 완전히 회피하지는 마세요",
          "focus": "균형과 위임을 통한 해방"
        }
      },
      
      "symbolism": [
        {"symbol": "10개의 무거운 완드", "meaning": "과도한 부담과 책임"},
        {"symbol": "구부정한 자세", "meaning": "짐의 무게로 인한 피로"},
        {"symbol": "가까운 마을", "meaning": "목표가 가까이 있음"},
        {"symbol": "혼자 걷는 모습", "meaning": "고독한 책임감"}
      ],
      
      "imageUrl": "assets/cards/wands_10_ten.png"
    },
    
    {
      "id": 32,
      "name": "Page of Wands",
      "koreanName": "완드 페이지",
      "suit": "wands",
      "number": 11,
      "element": "fire",
      "uprightKeywords": ["열정", "호기심", "모험", "새소식", "창의성", "자유정신", "탐험"],
      "reversedKeywords": ["성급함", "무책임", "방향상실", "산만함", "미성숙", "계획부족"],
      
      "interpretations": {
        "upright": {
          "general": "새로운 아이디어나 기회에 대한 소식이 들려올 것입니다. 젊은 에너지와 열정으로 새로운 모험을 시작할 수 있는 시기입니다.",
          "love": "젊고 열정적인 사람과의 만남이 있거나, 관계에 새로운 활력이 불어날 것입니다. 자유롭고 모험적인 연애를 경험할 수 있습니다.",
          "career": "새로운 프로젝트나 창의적인 업무에 대한 기회가 찾아옵니다. 젊은 동료나 후배로부터 도움을 받을 수 있습니다.",
          "money": "새로운 수입원에 대한 아이디어나 정보를 얻게 됩니다. 창의적이고 혁신적인 투자 기회가 있을 수 있습니다.",
          "health": "새로운 운동이나 건강법을 시도해볼 좋은 시기입니다. 활기찬 에너지로 건강 상태가 개선될 것입니다.",
          "spiritual": "영적 성장에 대한 새로운 관점이나 가르침을 접하게 됩니다. 자유로운 정신으로 영적 탐험을 시작할 수 있습니다."
        },
        "reversed": {
          "general": "좋은 아이디어는 있지만 실행력이 부족하거나 너무 성급하게 행동하려 합니다. 계획을 더 구체적으로 세워야 합니다.",
          "love": "연애에서 성급하거나 무책임한 행동을 할 수 있습니다. 상대방의 감정을 더 배려하고 신중하게 접근하세요.",
          "career": "새로운 기회가 있지만 준비가 부족하거나 너무 여러 가지를 동시에 시도하려 합니다. 집중력이 필요합니다.",
          "money": "투자나 사업 아이디어가 현실성이 부족하거나 충분한 계획 없이 시작하려 할 수 있습니다. 신중한 검토가 필요합니다.",
          "health": "건강 관리에 일관성이 부족하거나 극단적인 방법을 시도하려 할 수 있습니다. 균형잡힌 접근이 필요합니다.",
          "spiritual": "영적 성장에서 너무 성급하거나 피상적인 접근을 할 수 있습니다. 깊이 있는 수행이 필요합니다."
        }
      },
      
      "timing": {
        "immediate": "새로운 소식이나 기회가 곧 찾아옴",
        "shortTerm": "2-3주 동안 창의적 에너지가 활발",
        "longTerm": "2-3개월 후 새로운 모험의 첫 성과"
      },
      
      "advice": {
        "upright": {
          "action": "열정과 호기심을 가지고 새로운 기회를 탐색하세요",
          "avoid": "너무 보수적이 되어 기회를 놓치지 마세요",
          "focus": "창의성과 자유로운 사고"
        },
        "reversed": {
          "action": "계획을 더 구체적으로 세우고 신중하게 접근하세요",
          "avoid": "성급한 결정이나 무책임한 행동을 하지 마세요",
          "focus": "실행력과 책임감"
        }
      },
      
      "symbolism": [
        {"symbol": "젊은 페이지", "meaning": "새로운 시작과 가능성"},
        {"symbol": "완드를 바라보는 자세", "meaning": "호기심과 탐구심"},
        {"symbol": "깃털 모자", "meaning": "자유로운 정신"},
        {"symbol": "사막 배경", "meaning": "탐험과 모험의 영역"}
      ],
      
      "imageUrl": "assets/cards/wands_page.png"
    },
    
    {
      "id": 33,
      "name": "Knight of Wands",
      "koreanName": "완드 기사",
      "suit": "wands",
      "number": 12,
      "element": "fire",
      "uprightKeywords": ["행동력", "모험", "충동", "용기", "변화", "여행", "자신감"],
      "reversedKeywords": ["성급함", "무모함", "좌절", "지연", "방향감각상실", "충동조절부족"],
      
      "interpretations": {
        "upright": {
          "general": "강력한 행동력과 모험심으로 새로운 영역에 도전하게 됩니다. 변화와 이동이 많은 시기이며, 빠른 결정과 실행이 필요합니다.",
          "love": "열정적이고 로맨틱한 연애를 경험하게 됩니다. 적극적인 어프로치로 사랑을 쟁취하거나 관계에 큰 변화가 있을 수 있습니다.",
          "career": "새로운 프로젝트나 직무에 적극적으로 도전하게 됩니다. 출장이나 이직 등 큰 변화가 있을 수 있으며, 리더십을 발휘할 기회가 옵니다.",
          "money": "투자나 사업에서 과감한 결정을 내리게 됩니다. 빠른 수익을 얻을 가능성이 있지만 신중한 판단도 필요합니다.",
          "health": "활발한 활동으로 체력이 증진되고 에너지가 넘치게 됩니다. 새로운 운동이나 활동을 시작하기 좋은 시기입니다.",
          "spiritual": "영적 성장에서 적극적인 자세를 보이며 새로운 가르침이나 수행법에 도전하게 됩니다."
        },
        "reversed": {
          "general": "성급한 결정이나 무모한 행동으로 인해 어려움을 겪을 수 있습니다. 계획 없이 행동하다 좌절을 경험할 수 있습니다.",
          "love": "연애에서 너무 성급하거나 충동적인 행동으로 관계에 문제가 생길 수 있습니다. 상대방의 속도에 맞춰 조절이 필요합니다.",
          "career": "업무에서 성급한 결정이나 무리한 추진으로 문제가 발생할 수 있습니다. 팀워크보다는 독단적 행동을 주의해야 합니다.",
          "money": "충동적인 투자나 무계획적인 지출로 인해 재정적 손실을 볼 수 있습니다. 신중한 재검토가 필요합니다.",
          "health": "과도한 활동이나 무리한 운동으로 인해 부상이나 피로감을 느낄 수 있습니다. 적당한 조절이 필요합니다.",
          "spiritual": "영적 성장에서 성급함이나 자만심으로 인해 올바른 길을 벗어날 수 있습니다. 겸손한 자세가 필요합니다."
        }
      },
      
      "timing": {
        "immediate": "즉각적인 행동과 결정이 필요한 시점",
        "shortTerm": "2-4주 동안 활발한 활동과 변화",
        "longTerm": "3개월 후 빠른 행동의 결과가 명확해짐"
      },
      
      "advice": {
        "upright": {
          "action": "용기를 갖고 적극적으로 기회를 잡으세요",
          "avoid": "지나치게 신중해져서 기회를 놓치지 마세요",
          "focus": "행동력과 모험 정신"
        },
        "reversed": {
          "action": "속도를 조절하고 신중하게 계획을 세우세요",
          "avoid": "충동적인 결정이나 성급한 행동을 하지 마세요",
          "focus": "인내심과 계획적 접근"
        }
      },
      
      "symbolism": [
        {"symbol": "갑옷 입은 기사", "meaning": "용기와 보호"},
        {"symbol": "달리는 말", "meaning": "빠른 행동과 진전"},
        {"symbol": "깃털 투구", "meaning": "자유로운 정신"},
        {"symbol": "사막 풍경", "meaning": "모험과 도전의 영역"}
      ],
      
      "imageUrl": "assets/cards/wands_knight.png"
    },
    
    {
      "id": 34,
      "name": "Queen of Wands",
      "koreanName": "완드 여왕",
      "suit": "wands",
      "number": 13,
      "element": "fire",
      "uprightKeywords": ["자신감", "독립", "결단력", "온화함", "사교성", "직감", "리더십"],
      "reversedKeywords": ["질투", "이기심", "완고함", "짜증", "불안정", "자신감부족", "독단"],
      
      "interpretations": {
        "upright": {
          "general": "강한 자신감과 따뜻한 카리스마로 다른 사람들을 이끄는 시기입니다. 직감력이 뛰어나며 독립적으로 목표를 달성할 수 있습니다.",
          "love": "매력적이고 자신감 넘치는 모습으로 연애에서 주도권을 갖게 됩니다. 따뜻하면서도 독립적인 관계를 만들어갈 수 있습니다.",
          "career": "직장에서 리더십과 결단력을 인정받게 됩니다. 사교성과 소통 능력으로 팀을 잘 이끌고 성과를 거둘 수 있습니다.",
          "money": "재정 관리에서 현명한 판단력을 발휘합니다. 직감과 경험을 바탕으로 좋은 투자 결정을 내릴 수 있습니다.",
          "health": "건강에 대한 자신감과 활력이 넘치는 시기입니다. 균형잡힌 라이프스타일로 건강을 잘 유지할 수 있습니다.",
          "spiritual": "영적 성장에서 자신만의 길을 찾고 다른 사람들에게 영감을 주는 존재가 됩니다."
        },
        "reversed": {
          "general": "자신감이 부족하거나 반대로 지나친 자만심으로 인해 문제가 생길 수 있습니다. 다른 사람들과의 관계에서 갈등이 있을 수 있습니다.",
          "love": "연애에서 질투심이나 독점욕이 강해져 관계에 문제가 생길 수 있습니다. 상대방에게 너무 많은 것을 요구하지 마세요.",
          "career": "직장에서 독단적이거나 완고한 태도로 인해 동료들과 갈등을 빚을 수 있습니다. 다른 사람의 의견도 들어보세요.",
          "money": "재정 관리에서 감정적인 결정을 내리거나 과신으로 인해 손실을 볼 수 있습니다. 객관적인 판단이 필요합니다.",
          "health": "건강에 대한 과신이나 무관심으로 인해 문제가 생길 수 있습니다. 정기적인 검진과 관리가 필요합니다.",
          "spiritual": "영적 성장에서 자만심이나 편견으로 인해 진정한 깨달음을 얻기 어려울 수 있습니다."
        }
      },
      
      "timing": {
        "immediate": "자신감과 리더십을 발휘해야 할 시점",
        "shortTerm": "4-6주 동안 독립성과 결단력이 빛나는 시기",
        "longTerm": "6개월 후 카리스마 있는 리더로 성장"
      },
      
      "advice": {
        "upright": {
          "action": "자신감을 갖고 리더십을 발휘하되 따뜻함을 잃지 마세요",
          "avoid": "너무 독립적이 되어 다른 사람들을 소외시키지 마세요",
          "focus": "균형잡힌 리더십과 소통"
        },
        "reversed": {
          "action": "겸손한 자세로 다른 사람들의 의견을 들어보세요",
          "avoid": "질투심이나 독단적 태도를 보이지 마세요",
          "focus": "협력과 상호 존중"
        }
      },
      
      "symbolism": [
        {"symbol": "황금 왕좌", "meaning": "권위와 안정"},
        {"symbol": "해바라기", "meaning": "긍정성과 충성"},
        {"symbol": "검은 고양이", "meaning": "직감과 독립성"},
        {"symbol": "완드", "meaning": "창조적 힘과 리더십"}
      ],
      
      "imageUrl": "assets/cards/wands_queen.png"
    },
    
    {
      "id": 35,
      "name": "King of Wands",
      "koreanName": "완드 왕",
      "suit": "wands",
      "number": 14,
      "element": "fire",
      "uprightKeywords": ["리더십", "비전", "기업가정신", "성숙함", "권위", "영감", "자신감"],
      "reversedKeywords": ["독재", "성급함", "무능함", "오만", "충동", "방향상실", "권위남용"],
      
      "interpretations": {
        "upright": {
          "general": "성숙한 리더십과 강력한 비전으로 큰 성과를 이루는 시기입니다. 다른 사람들에게 영감을 주며 목표를 달성하는 능력이 뛰어납니다.",
          "love": "관계에서 성숙하고 안정된 모습을 보이며, 파트너에게 든든한 버팀목이 됩니다. 책임감 있는 사랑을 보여줄 수 있습니다.",
          "career": "직장에서 최고의 리더십을 발휘하며 큰 프로젝트나 사업을 성공적으로 이끕니다. 기업가적 정신으로 새로운 기회를 창출합니다.",
          "money": "재정적 성공과 안정을 이루며, 투자나 사업에서 탁월한 성과를 거둡니다. 장기적인 부의 축적이 가능합니다.",
          "health": "건강에 대한 강한 의지력과 관리 능력을 보입니다. 활력이 넘치며 다른 사람들에게도 건강한 영향을 미칩니다.",
          "spiritual": "영적 성장에서 깊은 지혜와 통찰력을 얻으며, 다른 사람들의 영적 스승 역할을 할 수 있습니다."
        },
        "reversed": {
          "general": "리더십이 독재적이 되거나 성급한 결정으로 인해 문제가 생길 수 있습니다. 권위를 남용하거나 오만한 태도를 보일 수 있습니다.",
          "love": "관계에서 지나치게 지배적이거나 독단적인 모습을 보일 수 있습니다. 파트너의 의견을 무시하거나 강압적일 수 있습니다.",
          "career": "직장에서 독재적인 리더십이나 무능함으로 인해 팀이나 프로젝트에 문제가 생길 수 있습니다. 권위에만 의존하려 합니다.",
          "money": "재정 관리에서 오만하거나 성급한 결정으로 큰 손실을 볼 수 있습니다. 위험한 투자나 사업에 무모하게 뛰어들 수 있습니다.",
          "health": "건강에 대한 과신으로 인해 관리를 소홀히 하거나, 스트레스로 인한 건강 문제가 생길 수 있습니다.",
          "spiritual": "영적 성장에서 자만심이나 교만으로 인해 진정한 지혜를 얻기 어려울 수 있습니다. 겸손함이 필요합니다."
        }
      },
      
      "timing": {
        "immediate": "리더십과 권위를 발휘해야 할 중요한 시점",
        "shortTerm": "6-8주 동안 최고의 성과와 성취",
        "longTerm": "1년 후 확고한 지위와 성공적인 결과"
      },
      
      "advice": {
        "upright": {
          "action": "비전을 제시하고 다른 사람들을 이끌어 목표를 달성하세요",
          "avoid": "성공에 안주하거나 독단적이 되지 마세요",
          "focus": "성숙한 리더십과 영감을 주는 비전"
        },
        "reversed": {
          "action": "겸손한 자세로 다른 사람들의 의견을 존중하세요",
          "avoid": "권위를 남용하거나 독재적인 태도를 보이지 마세요",
          "focus": "협력적 리더십과 겸손함"
        }
      },
      
      "symbolism": [
        {"symbol": "화려한 왕좌", "meaning": "권위와 성취"},
        {"symbol": "도마뱀", "meaning": "변화 적응력과 생존 능력"},
        {"symbol": "사자", "meaning": "용기와 왕의 위엄"},
        {"symbol": "완드", "meaning": "창조적 힘과 지배력"}
      ],
      
      "imageUrl": "assets/cards/wands_king.png"
    }
  ]
}